CHANGES.txt
CONTRIBUTORS.txt
README.txt
setup.cfg
setup.py
betahaus/__init__.py
betahaus.debug.egg-info/PKG-INFO
betahaus.debug.egg-info/SOURCES.txt
betahaus.debug.egg-info/dependency_links.txt
betahaus.debug.egg-info/entry_points.txt
betahaus.debug.egg-info/namespace_packages.txt
betahaus.debug.egg-info/not-zip-safe
betahaus.debug.egg-info/requires.txt
betahaus.debug.egg-info/top_level.txt
betahaus/debug/__init__.py
betahaus/debug/config.py
betahaus/debug/configure.zcml
betahaus/debug/setuphandlers.py
betahaus/debug/Extensions/__init__.py
betahaus/debug/Extensions/debug.py
betahaus/debug/profiles/default/betahaus.debug.various.txt
betahaus/debug/profiles/default/import_steps.xml
betahaus/debug/profiles/default/metadata.xml