Metadata-Version: 1.0
Name: betahaus.debug
Version: 0.1
Summary: Simple debug help with pdb
Home-page: http://pypi.python.org/pypi/betahaus.debug
Author: Martin Lundwall
Author-email: martin@betahaus.net
License: GPL
Keywords: plone debug pdb
Platform: UNKNOWN
Classifier: Framework :: Plone
Classifier: Intended Audience :: Developers
Classifier: Topic :: Software Development :: Libraries :: Python Modules
Classifier: License :: OSI Approved :: GNU General Public License (GPL)
